Package_1/Compare_Txt_Class.py
Package_1/Convert_File_Extension_Class.py
Package_1/Convert_Pdf_Class.py
Package_1/File_Handler_Class.py
Package_1/Read_Filenames_Dir_Class.py
Package_1/__init__.py
Package_2/Create_Windows_Class.py
Package_2/__init__.py
Pdf_check_fraud-0.0.1.dist-info/METADATA
Pdf_check_fraud-0.0.1.dist-info/WHEEL
Pdf_check_fraud-0.0.1.dist-info/license.txt
Pdf_check_fraud-0.0.1.dist-info/top_level.txt
Pdf_check_fraud-0.0.1.dist-info/RECORD
